{"cameraMode":{"drawMode":0,"name":"Shaded","section":"Shading Mode"},"sceneLighting":false,"audioPlay":false,"sceneViewState":{"m_AlwaysRefresh":false,"showFog":true,"showSkybox":false,"showFlares":true,"showImageEffects":true,"showParticleSystems":true,"showVisualEffectGraphs":true,"m_FxEnabled":true},"in2DMode":false,"pivot":{"x":21.53622055053711,"y":0.7295531630516052,"z":2.7043673992156984},"rotation":{"x":0.07912782579660416,"y":-0.7584432363510132,"z":0.09377975761890412,"w":0.6402322053909302},"size":1.2019000053405762,"orthographic":false}