{"cameraMode":{"drawMode":0,"name":"Shaded","section":"Shading Mode"},"sceneLighting":false,"audioPlay":false,"sceneViewState":{"m_AlwaysRefresh":false,"showFog":true,"showSkybox":false,"showFlares":true,"showImageEffects":true,"showParticleSystems":true,"showVisualEffectGraphs":true,"m_FxEnabled":true},"in2DMode":false,"pivot":{"x":1.5,"y":0.2329999953508377,"z":1.8700000047683716},"rotation":{"x":-0.09144915640354157,"y":0.07105220854282379,"z":-0.0065306406468153,"w":-0.9932680726051331},"size":10.0,"orthographic":false}